osu_data/.env
osu_data/__init__.py
osu_data/docker-compose.yml
osu_data/main.py
osu_data/nginx/404.html
osu_data/nginx/local.conf
osu_data/osu.files.Dockerfile
osu_data/osu.files.entrypoint.sh
osu_data/osu.files.healthcheck.sh
osu_data/osu.mysql.cnf
osu_data/osu.mysql.dl.Dockerfile
osu_data/osu.mysql.dl.entrypoint.sh
osu_data/osu.mysql.Dockerfile
osu_data/osu.mysql.healthcheck.sh
osu_data/scripts/get_maps.sh
osu_data-0.2.2.dist-info/entry_points.txt
osu_data-0.2.2.dist-info/METADATA
osu_data-0.2.2.dist-info/WHEEL
osu_data-0.2.2.dist-info/RECORD
