Metadata-Version: 2.1
Name: osu-data
Version: 0.2.2
Summary: Containerize osu! data into a MySQL container and optionally serve .osu files via NGINX
Home-page: https://github.com/Eve-ning/osu-data
License: MIT
Author: Eve-ning
Author-email: dev_evening@hotmail.com
Requires-Python: >=3.9,<4
Classifier: License :: OSI Approved :: MIT License
Classifier: Programming Language :: Python :: 3
Classifier: Programming Language :: Python :: 3.9
Classifier: Programming Language :: Python :: 3.10
Classifier: Programming Language :: Python :: 3.11
